eqlm/__init__.py
eqlm/__main__.py
eqlm/cli.py
eqlm/clipboard.py
eqlm/img.py
eqlm/io.py
eqlm/py.typed
eqlm/types.py
eqlm/utils.py
eqlm/desc/__init__.py
eqlm/desc/core.py
eqlm/desc/main.py
eqlm/eq/__init__.py
eqlm/eq/core.py
eqlm/eq/main.py
eqlm/laps/__init__.py
eqlm/laps/core.py
eqlm/laps/main.py
eqlm/match/__init__.py
eqlm/match/core.py
eqlm/match/main.py
eqlm-2.2.0.dist-info/licenses/LICENSE
eqlm-2.2.0.dist-info/METADATA
eqlm-2.2.0.dist-info/WHEEL
eqlm-2.2.0.dist-info/entry_points.txt
eqlm-2.2.0.dist-info/top_level.txt
eqlm-2.2.0.dist-info/RECORD
