Metadata-Version: 2.4
Name: eqlm
Version: 2.2.0
Summary: A CLI tool to manipulate images in various ways
Maintainer-email: curegit <contact@curegit.jp>
License-Expression: AGPL-3.0-or-later
Project-URL: homepage, https://github.com/curegit/eqlm
Project-URL: repository, https://github.com/curegit/eqlm.git
Keywords: image processing,image manipulation,brightness,saturation,lightness,histogram matching
Classifier: Programming Language :: Python :: 3 :: Only
Classifier: Topic :: Multimedia :: Graphics
Classifier: Topic :: Scientific/Engineering :: Image Processing
Classifier: Typing :: Typed
Requires-Python: >=3.12
License-File: LICENSE
Requires-Dist: numpy>=1.26.0
Requires-Dist: scipy>=1.15.0
Requires-Dist: opencv-python>=4.11.0
Requires-Dist: pillow>=9.3.0
Requires-Dist: scikit-image>=0.25.0
Provides-Extra: clipboard
Requires-Dist: pyside6; extra == "clipboard"
Provides-Extra: dev
Requires-Dist: pip; extra == "dev"
Requires-Dist: build; extra == "dev"
Requires-Dist: twine; extra == "dev"
Requires-Dist: black; extra == "dev"
Requires-Dist: mypy; extra == "dev"
Requires-Dist: coverage; extra == "dev"
Requires-Dist: scipy-stubs; extra == "dev"
Dynamic: license-file
